.clang-format
.cmake-format
.gitignore
CHANGELOG.md
CMakeLists.txt
LICENSE.md
README.md
codespellignore
config.h.cmake
dune-iga.pc.in
dune.module
pyproject.toml
setup.py
.github/workflows/createRelease.yml
.github/workflows/debian-coverage.yml
.github/workflows/debian.yml
.github/workflows/ghpages.yml
.github/workflows/releasePythonPackage.yml
.github/workflows/style.yml
.github/workflows/scripts/release.py
.reuse/dep5
LICENSES/CC0-1.0.txt
LICENSES/LGPL-3.0-or-later.txt
cmake/CMakeLists.txt
cmake/FormatTarget/CMakeLists.txt
cmake/FormatTarget/CPM.cmake
cmake/modules/AddAutoDiffFlags.cmake
cmake/modules/AddClipperLibFlags.cmake
cmake/modules/AddEarCutFlags.cmake
cmake/modules/AddEigenFlags.cmake
cmake/modules/AddnLohmannJsonFlags.cmake
cmake/modules/CMakeLists.txt
cmake/modules/DuneIgaMacros.cmake
doc/CMakeLists.txt
doc/markdownlint-config.yaml
doc/doxygen/CMakeLists.txt
doc/doxygen/Doxylocal
doc/doxygen/custom.css
doc/doxygen/mainpage.hh
dune/CMakeLists.txt
dune/iga/CMakeLists.txt
dune/iga/bsplinealgorithms.hh
dune/iga/controlpoint.hh
dune/iga/gridcapabilities.hh
dune/iga/nurbsalgorithms.hh
dune/iga/nurbsbasis.hh
dune/iga/nurbsgeometry.hh
dune/iga/nurbsgrid.hh
dune/iga/nurbsgridentity.hh
dune/iga/nurbsgridindexsets.hh
dune/iga/nurbsgridleafiterator.hh
dune/iga/nurbsgridtraits.hh
dune/iga/nurbsidset.hh
dune/iga/nurbsintersection.hh
dune/iga/nurbsleafgridview.hh
dune/iga/nurbslocalgeometry.hh
dune/iga/nurbspatch.hh
dune/iga/nurbspatchdata.hh
dune/iga/nurbspatchgeometry.hh
dune/iga/geometry/CMakeLists.txt
dune/iga/geometry/closestpointprojection.hh
dune/iga/geometry/geohelper.hh
dune/iga/io/CMakeLists.txt
dune/iga/io/igadatacollector.hh
dune/iga/io/igarefinedgeometries.hh
dune/iga/io/ibra/CMakeLists.txt
dune/iga/io/ibra/ibrageometry.hh
dune/iga/io/ibra/ibrareader.hh
dune/iga/test/CMakeLists.txt
dune/iga/test/concepttests.cpp
dune/iga/test/gridtests.cpp
dune/iga/test/trimmedgridtests.cpp
dune/iga/test/auxiliaryfiles/element.ibra
python/dune_iga.egg-info/PKG-INFO
python/dune_iga.egg-info/SOURCES.txt
python/dune_iga.egg-info/dependency_links.txt
python/dune_iga.egg-info/requires.txt
python/dune_iga.egg-info/top_level.txt
