Metadata-Version: 2.1
Name: dune-iga
Version: 0.1.8.dev20240618144352
Home-page: 
Author: mueller@ibb.uni-stuttgart.de
Author-email: mueller@ibb.uni-stuttgart.de
Classifier: Programming Language :: C++
Classifier: Programming Language :: Python :: 3
Classifier: License :: OSI Approved :: GNU General Public License (GPL)
Requires-Python: >=3.4
License-File: LICENSE.md
Requires-Dist: scipy
Requires-Dist: dune-functions<=2.9.0
Requires-Dist: numpy
Requires-Dist: dune-alugrid<=2.9.0
Requires-Dist: mpi4py
Requires-Dist: geomdl
Requires-Dist: dune-grid<=2.9.0
